plain/esbuild/CHANGELOG.md
plain/esbuild/README.md
plain/esbuild/__init__.py
plain/esbuild/cli.py
plain/esbuild/core.py
plain/esbuild/entrypoints.py
plain_esbuild-0.7.1.dist-info/METADATA
plain_esbuild-0.7.1.dist-info/WHEEL
plain_esbuild-0.7.1.dist-info/entry_points.txt
plain_esbuild-0.7.1.dist-info/licenses/LICENSE
plain_esbuild-0.7.1.dist-info/RECORD
