Metadata-Version: 2.4
Name: plain.esbuild
Version: 0.7.1
Summary: Build JavaScript files with esbuild.
Author-email: Dave Gaeddert <dave.gaeddert@dropseed.dev>
License-Expression: BSD-3-Clause
License-File: LICENSE
Requires-Python: >=3.13
Requires-Dist: plain<1.0.0
